Metadata-Version: 2.4
Name: impresso_essentials
Version: 1.3.3
Summary: Python module highly reusable within impresso.
Author-email: Pauline Conti <pauline.conti@epfl.ch>, Maud Ehrmann <maud.ehrmann@epfl.ch>, Matteo Romanello <matteo.romanello@gmail.com>
License:                     GNU GENERAL PUBLIC LICENSE
Project-URL: Homepage, https://github.com/impresso/impresso-essentials
Project-URL: Documentaton, https://impresso-essentials.readthedocs.io/en/latest/
Classifier: Programming Language :: Python :: 3
Classifier: Intended Audience :: Developers
Classifier: Intended Audience :: Science/Research
Classifier: License :: OSI Approved :: GNU Affero General Public License v3 or later (AGPLv3+)
Classifier: Operating System :: OS Independent
Classifier: Programming Language :: Python :: 3 :: Only
Classifier: Programming Language :: Python :: 3.10
Classifier: Programming Language :: Python :: 3.11
Classifier: Programming Language :: Python :: 3.12
Requires-Python: >=3.10
Requires-Dist: boto3==1.35.21
Requires-Dist: botocore==1.35.21
Requires-Dist: dask>=2024.9.0
Requires-Dist: dask-expr>=1.1.14
Requires-Dist: distributed>=2024.9.0
Requires-Dist: docopt==0.6.2
Requires-Dist: GitPython==3.1.44
Requires-Dist: importlib_resources==6.4.5
Requires-Dist: jsonschema==4.23.0
Requires-Dist: nltk==3.9.1
Requires-Dist: numpy==2.2.1
Requires-Dist: pandas>=2.2.2
Requires-Dist: pyarrow>=17.0.0
Requires-Dist: pysbd==0.3.4
Requires-Dist: pytest==8.3.3
Requires-Dist: python-dotenv==1.0.1
Requires-Dist: s3fs>=2024.9.0
Requires-Dist: setuptools==74.1.2
Requires-Dist: smart_open==7.0.4
Requires-Dist: StrEnum==0.4.15
Requires-Dist: tqdm==4.66.5
Requires-Dist: typing_extensions==4.12.2
Requires-Dist: sphinx-rtd-theme>=2.0.0
